email_relay/__init__.py
email_relay/apps.py
email_relay/backend.py
email_relay/conf.py
email_relay/db.py
email_relay/email.py
email_relay/models.py
email_relay/py.typed
email_relay/relay.py
email_relay/service.py
email_relay/management/__init__.py
email_relay/management/commands/__init__.py
email_relay/management/commands/runrelay.py
email_relay/migrations/0001_initial.py
email_relay/migrations/0002_auto_20231030_1304.py
email_relay/migrations/__init__.py
django_email_relay-0.6.0.dist-info/METADATA
django_email_relay-0.6.0.dist-info/WHEEL
django_email_relay-0.6.0.dist-info/licenses/AUTHORS.md
django_email_relay-0.6.0.dist-info/licenses/LICENSE
django_email_relay-0.6.0.dist-info/RECORD
