Metadata-Version: 2.4
Name: django-email-relay
Version: 0.6.0
Summary: Centralize and relay email from multiple distributed Django projects to an internal SMTP server via a database queue.
Project-URL: Documentation, https://django-email-relay.westervelt.dev/
Project-URL: Issues, https://github.com/westerveltco/django-email-relay/issues
Project-URL: Source, https://github.com/westerveltco/django-email-relay
Author-email: Josh Thomas <josh@joshthomas.dev>
License: MIT License
License-File: AUTHORS.md
License-File: LICENSE
Classifier: Development Status :: 4 - Beta
Classifier: Framework :: Django
Classifier: Framework :: Django :: 4.2
Classifier: Framework :: Django :: 5.1
Classifier: Framework :: Django :: 5.2
Classifier: License :: OSI Approved :: MIT License
Classifier: Operating System :: OS Independent
Classifier: Programming Language :: Python
Classifier: Programming Language :: Python :: 3
Classifier: Programming Language :: Python :: 3 :: Only
Classifier: Programming Language :: Python :: 3.9
Classifier: Programming Language :: Python :: 3.10
Classifier: Programming Language :: Python :: 3.11
Classifier: Programming Language :: Python :: 3.12
Classifier: Programming Language :: Python :: Implementation :: CPython
Requires-Python: >=3.9
Requires-Dist: django>=4.2
Provides-Extra: hc
Requires-Dist: requests; extra == 'hc'
Provides-Extra: psycopg
Requires-Dist: psycopg[binary]; extra == 'psycopg'
Provides-Extra: relay
Requires-Dist: environs[django]; extra == 'relay'
